robo/__init__.py
robo/exceptions.py
robo/streamwrappers.py
robo/models/__init__.py
robo/models/cache.py
robo/models/models_legacy.py
robo/testing/__init__.py
robo/testing/fakeanthropic.py
robo/testing/testbots.py
robo/testing/unittests/__init__.py
robo/tools/__init__.py
robo/utils/__init__.py
robo/utils/checkapi.py
robo/utils/consolestyle.py
robo/utils/interlocute.py
roboop-0.7.2.dist-info/licenses/LICENSE.txt
roboop-0.7.2.dist-info/METADATA
roboop-0.7.2.dist-info/WHEEL
roboop-0.7.2.dist-info/top_level.txt
roboop-0.7.2.dist-info/RECORD
