Metadata-Version: 2.4
Name: RoboOp
Version: 0.7.2
Summary: A microframework designed to get you started quickly building Claude-powered agents, assistants and applications with the Anthropic API.
Author-email: Alan Rowarth <alan@codex.cx>
License-Expression: MIT
Project-URL: Repository, https://github.com/ajrowr/RoboOp
Project-URL: Documentation, https://github.com/ajrowr/RoboOp/blob/master/docs/cookbook.md
Keywords: ai,claude,chatbot,anthropic,agent,assistant,llm,large-language-model,conversational-ai,bot-framework,streaming,tool-use,microframework,api-wrapper
Classifier: Development Status :: 4 - Beta
Classifier: Intended Audience :: Developers
Classifier: Intended Audience :: Science/Research
Classifier: Topic :: Scientific/Engineering :: Artificial Intelligence
Classifier: Topic :: Software Development :: Libraries :: Python Modules
Classifier: Topic :: Communications :: Chat
Classifier: Topic :: Internet :: WWW/HTTP :: Dynamic Content
Classifier: Programming Language :: Python :: 3
Classifier: Programming Language :: Python :: 3.10
Classifier: Programming Language :: Python :: 3.11
Classifier: Programming Language :: Python :: 3.12
Classifier: Programming Language :: Python :: 3.13
Classifier: Programming Language :: Python :: 3.14
Classifier: Operating System :: OS Independent
Classifier: Framework :: AsyncIO
Classifier: Environment :: Console
Classifier: Environment :: Web Environment
Classifier: Natural Language :: English
Classifier: Typing :: Typed
Requires-Python: >=3.10
License-File: LICENSE.txt
Requires-Dist: anthropic
Requires-Dist: platformdirs>=4.5.0
Dynamic: license-file
